flujo/__init__.py
flujo/builtins_architect.py
flujo/builtins_context.py
flujo/builtins_core.py
flujo/builtins_extras.py
flujo/builtins_extras_transforms.py
flujo/builtins_optional.py
flujo/builtins_support.py
flujo/cost.py
flujo/exceptions.py
flujo/py.typed
flujo/signature_tools.py
flujo/agents/__init__.py
flujo/agents/agent_like.py
flujo/agents/factory.py
flujo/agents/monitoring.py
flujo/agents/recipes.py
flujo/agents/repair.py
flujo/agents/utils.py
flujo/agents/wrapper.py
flujo/agents/adapters/__init__.py
flujo/agents/adapters/pydantic_ai_adapter.py
flujo/application/__init__.py
flujo/application/eval_adapter.py
flujo/application/evaluators.py
flujo/application/run_plan_resolver.py
flujo/application/run_session.py
flujo/application/runner.py
flujo/application/runner_execution.py
flujo/application/runner_methods.py
flujo/application/self_improvement.py
flujo/application/temperature.py
flujo/application/tracer_resolver.py
flujo/application/tree_search_improvement.py
flujo/application/conversation/history_manager.py
flujo/application/core/README.md
flujo/application/core/__init__.py
flujo/application/core/agent_execution_runner.py
flujo/application/core/agent_fallback_handler.py
flujo/application/core/agent_handler.py
flujo/application/core/agent_orchestrator.py
flujo/application/core/agent_plugin_runner.py
flujo/application/core/async_iter.py
flujo/application/core/background_task_handler.py
flujo/application/core/background_task_manager.py
flujo/application/core/cache_manager.py
flujo/application/core/conditional_orchestrator.py
flujo/application/core/context_adapter.py
flujo/application/core/context_manager.py
flujo/application/core/context_strategies.py
flujo/application/core/context_update_manager.py
flujo/application/core/context_vars.py
flujo/application/core/default_cache_components.py
flujo/application/core/default_components.py
flujo/application/core/dispatch_handler.py
flujo/application/core/error_utils.py
flujo/application/core/estimation.py
flujo-0.6.4.dist-info/METADATA
flujo-0.6.4.dist-info/WHEEL
flujo-0.6.4.dist-info/entry_points.txt
flujo-0.6.4.dist-info/licenses/LICENSE
flujo-0.6.4.dist-info/RECORD
