Metadata-Version: 2.4
Name: flujo
Version: 0.6.4
Summary: A modern, type-safe framework for building AI-powered applications with structured outputs and robust error handling.
Project-URL: Homepage, https://github.com/aandresalvarez/flujo
Project-URL: Repository, https://github.com/aandresalvarez/flujo
Project-URL: Documentation, https://aandresalvarez.github.io/flujo/
Project-URL: Bug_Tracker, https://github.com/aandresalvarez/flujo/issues
Project-URL: Changelog, https://github.com/aandresalvarez/flujo/blob/main/CHANGELOG.md
Author-email: Alvaro Andres Alvarez <aandresalvarez@gmail.com>
License: AGPL-3.0
License-File: LICENSE
Keywords: agent,ai,async,llm,pipeline,type-safe,workflow
Classifier: Development Status :: 4 - Beta
Classifier: Intended Audience :: Developers
Classifier: License :: OSI Approved :: GNU Affero General Public License v3
Classifier: Operating System :: OS Independent
Classifier: Programming Language :: Python :: 3
Classifier: Programming Language :: Python :: 3.13
Classifier: Programming Language :: Python :: 3.14
Classifier: Topic :: Scientific/Engineering :: Artificial Intelligence
Classifier: Topic :: Software Development :: Libraries :: Python Modules
Classifier: Typing :: Typed
Requires-Python: >=3.13
Requires-Dist: aiosqlite>=0.19.0
Requires-Dist: anyio>=4.0.0
Requires-Dist: blake3>=0.4.0
Requires-Dist: mcp>=1.23.0
Requires-Dist: numpy>=1.20.0
Requires-Dist: openai<3.0,>=2.1.0
Requires-Dist: orjson>=3.9.0
Requires-Dist: pydantic-ai<1.26.0,>=1.0.15
Requires-Dist: pydantic-evals>=0.4.7
Requires-Dist: pydantic-settings>=2.0.0
Requires-Dist: pydantic<2.13,>=2.11.7
Requires-Dist: pyyaml>=6.0
Requires-Dist: rich>=13.0.0
Requires-Dist: ruamel-yaml>=0.18
Requires-Dist: starlette>=0.49.1
Requires-Dist: tenacity>=8.2.0
Requires-Dist: typer>=0.16.1
Requires-Dist: uvloop>=0.19.0; sys_platform != 'win32'
Provides-Extra: aop-extras
Requires-Dist: json-repair>=0.16; extra == 'aop-extras'
Requires-Dist: pyjson5>=1.6; (python_version >= '3.8') and extra == 'aop-extras'
Provides-Extra: bench
Requires-Dist: numpy>=1.20.0; extra == 'bench'
Requires-Dist: pytest-benchmark>=4.0.0; extra == 'bench'
Provides-Extra: dev
Requires-Dist: bandit==1.7.9; extra == 'dev'
Requires-Dist: build==1.2.2.post1; extra == 'dev'
Requires-Dist: cyclonedx-python-lib==7.4.0; extra == 'dev'
Requires-Dist: httpx==0.28.1; extra == 'dev'
Requires-Dist: hypothesis==6.112.0; extra == 'dev'
Requires-Dist: logfire==4.0.0; extra == 'dev'
Requires-Dist: mypy==1.12.0; extra == 'dev'
Requires-Dist: pip-audit==2.7.3; extra == 'dev'
Requires-Dist: prometheus-client==0.22.1; extra == 'dev'
Requires-Dist: pytest-asyncio==0.24.0; extra == 'dev'
Requires-Dist: pytest-benchmark==4.0.0; extra == 'dev'
Requires-Dist: pytest-cov==5.0.0; extra == 'dev'
Requires-Dist: pytest-deadfixtures==2.2.1; extra == 'dev'
Requires-Dist: pytest-picked==0.4.6; extra == 'dev'
Requires-Dist: pytest-randomly==3.15.0; extra == 'dev'
Requires-Dist: pytest-rerunfailures==13.0; extra == 'dev'
Requires-Dist: pytest-split==0.10.0; extra == 'dev'
Requires-Dist: pytest-timeout==2.3.1; extra == 'dev'
Requires-Dist: pytest-xdist==3.6.1; extra == 'dev'
Requires-Dist: pytest==8.3.3; extra == 'dev'
Requires-Dist: ruff==0.14.10; extra == 'dev'
Requires-Dist: sqlvalidator==0.0.8; extra == 'dev'
Requires-Dist: twine==5.1.1; extra == 'dev'
Requires-Dist: vcrpy==6.0.1; extra == 'dev'
Provides-Extra: docker
Requires-Dist: docker>=7.0.0; (python_version < '3.13') and extra == 'docker'
Provides-Extra: docs
Requires-Dist: mkdocs; extra == 'docs'
Requires-Dist: mkdocs-material; extra == 'docs'
Requires-Dist: mkdocs-redirects; extra == 'docs'
Requires-Dist: mkdocstrings[python]; extra == 'docs'
Provides-Extra: lens
Requires-Dist: opentelemetry-exporter-otlp-proto-http<2.0,>=1.20; extra == 'lens'
Requires-Dist: opentelemetry-sdk<2.0,>=1.20; extra == 'lens'
Requires-Dist: prometheus-client<0.23.0,>=0.22.1; extra == 'lens'
Provides-Extra: logfire
Requires-Dist: logfire>=4.0.0; extra == 'logfire'
Provides-Extra: opentelemetry
Requires-Dist: opentelemetry-exporter-otlp-proto-http>=1.26; extra == 'opentelemetry'
Requires-Dist: opentelemetry-sdk>=1.26; extra == 'opentelemetry'
Provides-Extra: pii
Requires-Dist: presidio-analyzer>=2.2.0; extra == 'pii'
Requires-Dist: presidio-anonymizer>=2.2.0; extra == 'pii'
Provides-Extra: postgres
Requires-Dist: asyncpg>=0.29.0; extra == 'postgres'
Provides-Extra: prometheus
Requires-Dist: prometheus-client<0.23.0,>=0.22.1; extra == 'prometheus'
Provides-Extra: skills
Requires-Dist: aiofiles; extra == 'skills'
Requires-Dist: ddgs; extra == 'skills'
Requires-Dist: httpx; extra == 'skills'
Requires-Dist: pyfiglet; extra == 'skills'
Provides-Extra: sql
Requires-Dist: sqlvalidator>=0.0.8; extra == 'sql'
Provides-Extra: templating
Requires-Dist: jinja2>=3.1; extra == 'templating'
Provides-Extra: yaml-tools
Requires-Dist: ruamel-yaml>=0.18; extra == 'yaml-tools'
